LICENSE.txt
MANIFEST.in
README.rst
setup.py
coda_Kids/__init__.py
coda_Kids/color.py
coda_Kids/dir.py
coda_Kids/event.py
coda_Kids/state.py
coda_Kids/utilities.py
coda_kids/__init__.py
coda_kids/actions.py
coda_kids/color.py
coda_kids/dir.py
coda_kids/event.py
coda_kids/state.py
coda_kids/utilities.py
coda_kids.egg-info/PKG-INFO
coda_kids.egg-info/SOURCES.txt
coda_kids.egg-info/dependency_links.txt
coda_kids.egg-info/not-zip-safe
coda_kids.egg-info/requires.txt
coda_kids.egg-info/top_level.txt