Metadata-Version: 1.1
Name: coda-kids
Version: 0.2.3
Summary: Partial pygame wrapper and game programming framework.
Home-page: https://github.com/Coda-Kids/coda-kids
Author: Andrew Dillon
Author-email: AndrewDillon91@gmail.com
License: MIT
Platform: UNKNOWN
Classifier: Development Status :: 2 - Pre-Alpha
Classifier: License :: OSI Approved :: MIT License
Classifier: Programming Language :: Python :: 3
Classifier: Intended Audience :: Education
